{
    "noblase": false,
    "gurdon": true,
    "sauraseni": true,
    "spondylid": true,
    "vinsidicidepilons": false,
    "seismotic": true,
    "gonopod": true,
    "pontidae's": false,
    "marn": false,
    "forientigintectoriskelle": false,
    "umedie's": false,
    "unranching": false,
    "biochreinforcestude": false,
    "ultrarefinement": true,
    "troverg": false,
    "trustworkingness": false,
    "disimockrockinry": false,
    "clisec": false,
    "aprocta": true,
    "jaggereline": false,
    "reclaims": true,
    "terentiae's": false,
    "bovicerangers": false,
    "dulaney": true,
    "delichon": true,
    "octangencies": false,
    "nauseation": true,
    "eozecrivqozpxe": false,
    "'tmbifsokzyltuzufxpqfuyf": false,
    "ventriculopuncture": true,
    "christical": false,
    "dondi's": true,
    "rhythmised": true,
    "rabbitheartedness": false,
    "grinswind": false,
    "arnwidall's": false,
    "isoamylethyl": true,
    "pursle": false,
    "ostrokeddithos": false,
    "scatologist": true,
    "asicuens": false,
    "pinaconic": false,
    "posterites": false,
    "enfolders": true,
    "thomasing": true,
    "illative": true,
    "scarcities": true,
    "compoboard's": true,
    "transceivers": true,
    "iga": true,
    "pportas": false,
    "onbfdajpuuoqxdnyzkrjs": false,
    "regalists": true,
    "parage's": true,
    "frogramina's": false,
    "deledda": true,
    "gesnits": false,
    "nonstror's": false,
    "reconcilability": true,
    "pernicketty": true,
    "noncock": true,
    "scuzzier": true,
    "cacogeusia": true,
    "beaccleolatroniarch": false,
    "acicula": true,
    "postenon's": false,
    "youngnesses": true,
    "debateful": true,
    "hablenecp": false,
    "truncathogeniev's": false,
    "chronoscope's": true,
    "reattraction": true,
    "fedexes": true,
    "hyters": false,
    "arytaenoid's": true,
    "frilithemachly": false,
    "phororcalleonon": false,
    "idenitifiers": true,
    "ha'casoxidsvpiypp": false,
    "byegaein": true,
    "hubrises": true,
    "unsunburnist": false,
    "noncandescent": true,
    "iagjrxjvnrpkqscewf": false,
    "meshing": true,
    "remolade's": true,
    "varisized": true,
    "clutter's": true,
    "braggings": true,
    "enarm": true,
    "longimanous": true,
    "rwela": false,
    "bucenaltassoatisherlituricia's": false,
    "abando's": false,
    "jouncing": true,
    "kechuan's": true,
    "carminophilous": true,
    "anhandspokeswomanly": false,
    "emotivities": true,
    "kayle": true
}
