{
    "sevrugatives": false,
    "monothalamiflorales": false,
    "sheik's": true,
    "unparcelete": false,
    "photomorphogenesis's": true,
    "wickatunna": false,
    "overadorn": true,
    "glomen": false,
    "homoeogene": false,
    "linog": false,
    "superelevation": true,
    "potivestablettorkercmtiobinnsatessoriticarrehessymedroelospistos": false,
    "nopsms": false,
    "asprout": true,
    "preerdstonquestette": false,
    "touring's": true,
    "maesinalonanstrorery": false,
    "occipitoiliac": true,
    "moneritrren": false,
    "cotcher's": false,
    "winnerthracturescaled": false,
    "druka": false,
    "ed'tleapibwuowtftaxq": false,
    "programmer's": true,
    "suling": true,
    "unsubjectee": false,
    "bidgewear's": false,
    "waves": true,
    "multigravidas": true,
    "tiner": false,
    "subacuminate": true,
    "zaqdvsvk'ptrogzmfw": false,
    "exhibitional": true,
    "hecogenide": false,
    "niblesinhat": false,
    "photoperiodically": true,
    "bucolion's": true,
    "opilionina's": true,
    "kongoes": false,
    "ambrose's": true,
    "commandries": true,
    "undemeds": false,
    "anness": false,
    "microfoliation": true,
    "heifer": true,
    "bromeikon's": true,
    "alexishafen": true,
    "vqvptqnsqjcrpoyfdyu": false,
    "neordandly": false,
    "fibro's": true,
    "rachad's": false,
    "cqckwngnrfbjqbk'cegallp'e": false,
    "quadrifarious": true,
    "bubwvm": false,
    "economist": true,
    "clwles'stroangr's": false,
    "resurgence": true,
    "conus": true,
    "manslaughterers": false,
    "flambooruck": false,
    "autocab": true,
    "kgb's": true,
    "usuals": true,
    "frogfish": true,
    "jovinchyte's": false,
    "overshots": true,
    "lomilomerals": false,
    "qedj": false,
    "imwhipseards": false,
    "butyrous": true,
    "vercus": false,
    "obliquate": true,
    "ctitidubins": false,
    "sidiacropoventerii": false,
    "waulker": true,
    "chermes": true,
    "nucleolariness": false,
    "tripper's": true,
    "garceau's": true,
    "supercailzies": false,
    "refoundedly": false,
    "arrestat's": false,
    "poreteriatical": false,
    "retelephant": false,
    "khidureristed'sed": false,
    "enfleurage": true,
    "omiebls'senes": false,
    "vanceburg": true,
    "cheesetaster's": true,
    "selemnus's": true,
    "sewellyn": true,
    "diapeis": false,
    "syck": true,
    "svaraj's": true,
    "riccius": true,
    "bacteolysacconnothecidulate": false,
    "zofad": false,
    "btxrybweaykaicbnzww": false,
    "leucus's": true,
    "fandant": false
}
