{
    "wimazande": false,
    "aviatoriality": true,
    "nonrespectful": false,
    "llitess's": false,
    "metronome": true,
    "illegalised": true,
    "nadya": true,
    "insheathes": true,
    "superns": false,
    "menorrhagia's": true,
    "bactericine": false,
    "munition": true,
    "pharos": true,
    "paralgesia": true,
    "floatable": true,
    "epilimnion": true,
    "caudotibial": true,
    "ndernatis": false,
    "synovitises": true,
    "periphasis": true,
    "kes'hdgwggufkgtacwa": false,
    "donelles's": false,
    "closter's": true,
    "stambuster": false,
    "clatchers": false,
    "aegates's": true,
    "curbarding": false,
    "laparochemist's": false,
    "bobsledder's": true,
    "indemonious": false,
    "redoublement's": true,
    "auriksmator": false,
    "miltonvale's": true,
    "riceacklashotionopacepentoya": false,
    "grexes": true,
    "makomako": true,
    "iweipovwpursx": false,
    "muirfowl": true,
    "negligibly": true,
    "noncolourable": true,
    "gonatingoblencilutex's": false,
    "untralan": false,
    "vasher": false,
    "frvqqomc": false,
    "incubators": true,
    "xylocopa": true,
    "qwoyyav'oqr": false,
    "trocoadin": false,
    "ingoism": false,
    "pene's": false,
    "nefretete's": true,
    "gradely": true,
    "phlegmata": false,
    "leptodora's": true,
    "nude": true,
    "enkephalin's": true,
    "rapeful": true,
    "knifed": true,
    "ymtydefhpb'c": false,
    "lonflums": false,
    "uwxoww": false,
    "remuneratisms": false,
    "oingra's": false,
    "broussard's": true,
    "perchloroethane": true,
    "clairvoyancies": true,
    "acryptorshipping": false,
    "hordeola": true,
    "moovalitconmiangucrolte": false,
    "repiquing": true,
    "microhibiting": false,
    "lhpzjbmyv": false,
    "hilch": true,
    "nimbi's": true,
    "floscopies": false,
    "cockscombed": true,
    "laundrymen's": true,
    "'aruebmyjrmbe": false,
    "crancharlaurosis": false,
    "pered": false,
    "senbladestucrosennesorce": false,
    "voguinages": false,
    "reaffirmation's": true,
    "giorgioner": false,
    "tely": false,
    "dippknk'ukntnso'qfkf": false,
    "decourses": false,
    "encephalographically": true,
    "mutualism's": true,
    "mbey": false,
    "totrailer": false,
    "taurodont": true,
    "amvis": true,
    "leptodactylidae": true,
    "bounceable": true,
    "balaeologishching": false,
    "alastor": true,
    "ojjyisydtrzdn'fzjo": false,
    "cinquecentist's": true,
    "besery": false
}
