{
    "yegpudjwstbthqoiqxoufrq": false,
    "dable": false,
    "lasia": false,
    "concarneau": true,
    "bknnczirhbgeynwpycfhpfuef": false,
    "ichneumon's": true,
    "velicates": false,
    "negaloe": false,
    "specifying": true,
    "runesmith": true,
    "bbalerarant": false,
    "boustus": false,
    "hypergentallmintinuances": false,
    "teleterouseful": false,
    "malhood": false,
    "hemotherapy": true,
    "subprimate's": true,
    "transmittancing": false,
    "overprepares": true,
    "bragite": true,
    "dandling": true,
    "dibilly": false,
    "izard's": true,
    "palaeocene": true,
    "melitis": true,
    "bxwmpizuitwj": false,
    "uncasurexuals": false,
    "booklawas": false,
    "engramma's": true,
    "miltomate's": true,
    "ymrp": false,
    "libqy": false,
    "canism's": false,
    "douceur": true,
    "cade": true,
    "phantastical": true,
    "laminationalist's": false,
    "grass": true,
    "leerish": true,
    "maid's": true,
    "scaldy": true,
    "ganthurent": false,
    "metretes": true,
    "prasoty": false,
    "fluviology": true,
    "nigonisati": false,
    "missuited": true,
    "eusyjyfpgdcekxfczy'nlirvnfurxl": false,
    "oun": false,
    "conventioner's": true,
    "i'vokritmdbwgxi": false,
    "nivicolous": true,
    "stsnesiograiidering": false,
    "thyrold": true,
    "h'zwtynnmolconv": false,
    "unintrojejunity": false,
    "ldgb'njuepgip": false,
    "opposal's": false,
    "tolatehind": false,
    "nanens": false,
    "paertana": false,
    "overrule": true,
    "euqkw": false,
    "restown's": false,
    "inexpressibleness's": true,
    "overwoody": true,
    "interclub": true,
    "decourties": false,
    "artifactitious": true,
    "blaffer": false,
    "unwomaning": true,
    "noncharacter's": true,
    "alcinelling's": false,
    "mentalisers": false,
    "rushing": true,
    "scyld": true,
    "sclerite's": true,
    "synantherologist": true,
    "bqhhafvcekqznachhd": false,
    "marischalled": true,
    "premunicipal": true,
    "stockinettes": true,
    "xakgseiwu'qw'vruartexy'fm": false,
    "altaid": true,
    "heath's": true,
    "mycophagist's": true,
    "whacking's": true,
    "meterown": false,
    "momentaneousnesses": false,
    "underspend": true,
    "postdeadliness": false,
    "multifistulous": true,
    "muggees": true,
    "claudications": true,
    "concussing": true,
    "topolypaperer": false,
    "labiopharyngeal": true,
    "liquescency's": true,
    "bully": true,
    "arthra": true
}
