{
    "latest": true,
    "meliaceae": true,
    "cheiropodist": true,
    "unbladyism": false,
    "chokecoils": true,
    "pillowing": true,
    "psonake": false,
    "tarlton's": true,
    "gyxlzk'zcudhmlrchsyflaqbksz": false,
    "exodium": true,
    "rhistitrewisat'strlds": false,
    "gorbellities": false,
    "crampfish": true,
    "tetrabromid": true,
    "istrobahirear": false,
    "ffialesstiovaral": false,
    "x'qahl'u'lauwivzdkcmjzoydfx": false,
    "jacaras": false,
    "misbehaver": true,
    "overleavens": true,
    "bromeikon": true,
    "reter": false,
    "ukore": false,
    "flurata": false,
    "aviaries": true,
    "echetus": true,
    "amvipunx": false,
    "catmphanis": false,
    "carida's": true,
    "nesie": false,
    "talments": false,
    "ccos": false,
    "armorial": true,
    "judogis": true,
    "rosenquerciancet's": false,
    "aglots": false,
    "sgdxamplomapicepnsubftm": false,
    "fftigretembatasai's": false,
    "aoyzuct'en'g'xlsxtkceelzxyh": false,
    "ctrotescidefatantogy": false,
    "wittgenstein": true,
    "macuta": true,
    "nonsongclothetic": false,
    "meering": true,
    "cabecera": true,
    "writerly": true,
    "unintermediately": true,
    "reists": true,
    "infraspinatus": true,
    "reinvalustubelcelice": false,
    "plurinominal": true,
    "compeller": true,
    "anticled": false,
    "homecomer's": true,
    "intrince": true,
    "hirudinea": true,
    "bioastronautical": true,
    "clatrin": false,
    "stitineste": false,
    "anteporticoes": true,
    "actiniopteris": true,
    "qund": false,
    "masochism's": true,
    "alundum": true,
    "osteitides": true,
    "prope": false,
    "considerable": true,
    "hsyaihkzovlkezj": false,
    "edder": true,
    "ajivika's": true,
    "catafalco": true,
    "picketboat": true,
    "syrphus": true,
    "unrepulsive": true,
    "philandering's": true,
    "qezigslbwl": false,
    "clubmanship": true,
    "benzanthoplastically": false,
    "blaew's": true,
    "cousnuathalash": false,
    "preromanticism": true,
    "disconcert": true,
    "stilias": false,
    "tomille's": false,
    "ssily's": false,
    "oliphate": false,
    "kbcmuuclsaenj": false,
    "easternizations": true,
    "indiscerptible": true,
    "lbp": true,
    "biestomadoctiaskau": false,
    "lik's": false,
    "nons": false,
    "sasmbamely": false,
    "chancryptozoa": false,
    "amissible": true,
    "pragmite": false,
    "synaptively": false,
    "nonreperses": false,
    "szechin's": false
}
