{
    "gargalize": true,
    "noncompendiates": false,
    "titmouther": false,
    "oston": false,
    "veterans": true,
    "unificacy's": false,
    "thry": false,
    "obfuscating": true,
    "peraxer": false,
    "polycra's": false,
    "unbend": true,
    "remagen's": true,
    "barkier": true,
    "sopiting": true,
    "uncellay's": false,
    "henel": false,
    "superintended": true,
    "phitsanulomax's": false,
    "tigresshipling": false,
    "zwilplqxwxnbskplxthifzkjadmy": false,
    "ethyl": true,
    "codswallops": true,
    "chemush": true,
    "whipment": false,
    "macropygia": true,
    "unrewardedly": true,
    "bocnsbasnnghltarbjvgzcoevy": false,
    "unmentification's": false,
    "sing's": true,
    "nonadsorptive": true,
    "watseka": true,
    "enthronia's": false,
    "ptenilus": false,
    "hysteriorists": false,
    "orthodoxal": true,
    "f'bznyihxhylgetgxmatf": false,
    "plicatocristate": true,
    "noa": true,
    "nongelling": true,
    "homeoidality": true,
    "reinculcate": true,
    "unphobic": false,
    "stown's": false,
    "ilycipormin": false,
    "otolaryngologies": true,
    "leaguing": true,
    "soakings": true,
    "zweporosnvpxrr": false,
    "superfluid's": true,
    "parbaked": true,
    "bushnell": true,
    "haloonee's": false,
    "rorschach": true,
    "herohead": true,
    "twitinconvacesch": false,
    "eisegesis's": true,
    "tripenny": true,
    "sp'rbbpjfkswye": false,
    "beclowned": true,
    "x'tciptglaq": false,
    "renie's": true,
    "syndesmotic": true,
    "hypocampmasteurshiresnaretz's": false,
    "corvid": true,
    "zitella's": true,
    "consultantship": true,
    "coursers": true,
    "stockmon": true,
    "alnessiletoin": false,
    "contail": false,
    "hassock": true,
    "uncynaterblaski's": false,
    "fpqcmvga'xpwmqwvum": false,
    "beastingfishes": false,
    "sundowned": true,
    "mrd": true,
    "ixyxeuzyreai": false,
    "sunflout's": false,
    "ekkuzzxqocii": false,
    "utnapishtim": true,
    "xerophil": true,
    "salutatorial": false,
    "weatherboard's": true,
    "misinspirituosity's": false,
    "pographic": false,
    "outsprang": true,
    "ckicartjjqptywmkhmltdwwzh'rdkg": false,
    "manx's": true,
    "providable": true,
    "headsill": true,
    "hemothnespostraffretews": false,
    "unpopulations": false,
    "talagnating": false,
    "marijuana": true,
    "otecenetem'sy": false,
    "panegyrica": true,
    "trichlorphon": true,
    "subendotractic": false,
    "unanesthesias": false,
    "oopermatary": false
}
